collective.upgrade-1.5-py2.7-nspkg.pth
collective/upgrade/__init__.py
collective/upgrade/broken.py
collective/upgrade/broken.zcml
collective/upgrade/configure.zcml
collective/upgrade/interfaces.py
collective/upgrade/pas.py
collective/upgrade/pas.rst
collective/upgrade/ploneupgrader.py
collective/upgrade/portals.py
collective/upgrade/run.py
collective/upgrade/steps.py
collective/upgrade/steps.zcml
collective/upgrade/testing.py
collective/upgrade/testing.zcml
collective/upgrade/tests.py
collective/upgrade/upgrader.py
collective/upgrade/upgraders.zcml
collective/upgrade/utils.py
collective/upgrade/profiles/blank/actions.xml
collective/upgrade/profiles/blank/archetype_tool.xml
collective/upgrade/profiles/blank/browserlayer.xml
collective/upgrade/profiles/blank/cachingpolicymgr.xml
collective/upgrade/profiles/blank/catalog.xml
collective/upgrade/profiles/blank/contentrules.xml
collective/upgrade/profiles/blank/contenttyperegistry.xml
collective/upgrade/profiles/blank/controlpanel.xml
collective/upgrade/profiles/blank/cookieauth.xml
collective/upgrade/profiles/blank/cssregistry-bbb.xml
collective/upgrade/profiles/blank/cssregistry.xml
collective/upgrade/profiles/blank/diff_tool.xml
collective/upgrade/profiles/blank/factorytool.xml
collective/upgrade/profiles/blank/jsregistry-bbb.xml
collective/upgrade/profiles/blank/jsregistry.xml
collective/upgrade/profiles/blank/mailhost.xml
collective/upgrade/profiles/blank/memberdata_properties.xml
collective/upgrade/profiles/blank/portal_atct.xml
collective/upgrade/profiles/blank/portal_languages.xml
collective/upgrade/profiles/blank/portal_placeful_workflow.xml
collective/upgrade/profiles/blank/portlets.xml
collective/upgrade/profiles/blank/properties.xml
collective/upgrade/profiles/blank/propertiestool.xml
collective/upgrade/profiles/blank/reference_catalog.xml
collective/upgrade/profiles/blank/registry.xml
collective/upgrade/profiles/blank/repositorytool.xml
collective/upgrade/profiles/blank/rolemap.xml
collective.upgrade-1.5.dist-info/METADATA
collective.upgrade-1.5.dist-info/WHEEL
collective.upgrade-1.5.dist-info/entry_points.txt
collective.upgrade-1.5.dist-info/namespace_packages.txt
collective.upgrade-1.5.dist-info/top_level.txt
collective.upgrade-1.5.dist-info/RECORD
