Metadata-Version: 2.1
Name: collective.upgrade
Version: 1.5
Summary: CMF portal upgrade helpers
Home-page: http://github.com/collective/collective.upgrade
Author: Ross Patterson
Author-email: me@rpatterson.net
License: GPL
Keywords: Zope CMF Plone GenericSetup upgrade
Platform: UNKNOWN
Classifier: Framework :: Plone
Classifier: Programming Language :: Python
Classifier: Topic :: Software Development :: Libraries :: Python Modules
Requires-Dist: setuptools
Requires-Dist: zope.globalrequest
Requires-Dist: zodbupdate
Requires-Dist: Products.GenericSetup
Requires-Dist: Products.CMFCore
Provides-Extra: steps
Requires-Dist: experimental.broken ; extra == 'steps'
Requires-Dist: collective.setdefaulteditor ; extra == 'steps'
Provides-Extra: test
Requires-Dist: plone.app.testing ; extra == 'test'
